Metadata-Version: 2.1
Name: template-pptx-jinja-my
Version: 0.0.2
Summary: PowerPoint presentation builder from template using Jinja2
Home-page: https://github.com/macheal/template-pptx-jinja
Author: macheal
Author-email: xinyukc01@icloud.com
Keywords: powerpoint,ppt,pptx,template
Classifier: Development Status :: 4 - Beta
Classifier: Topic :: Utilities
Classifier: Programming Language :: Python :: 3
Classifier: License :: OSI Approved :: GNU General Public License v3 (GPLv3)
Classifier: Operating System :: OS Independent
License-File: LICENSE
Requires-Dist: jinja2 (==3.1.2)
Requires-Dist: python-pptx (==0.6.21)
